git_analytics/__init__.py
git_analytics/analyzers/__init__.py
git_analytics/analyzers/authors_statistics.py
git_analytics/analyzers/commit_type.py
git_analytics/analyzers/commits_summary.py
git_analytics/analyzers/historical_statistics.py
git_analytics/analyzers/language_statistics.py
git_analytics/analyzers/lines_statistics.py
git_analytics/engine.py
git_analytics/entities.py
git_analytics/helpers.py
git_analytics/interfaces.py
git_analytics/main.py
git_analytics/sources/__init__.py
git_analytics/sources/git_commit_adapter.py
git_analytics/sources/git_log_adapter.py
git_analytics/static/css/bootstrap-icons.min.css
git_analytics/static/css/bootstrap.min.css
git_analytics/static/css/fonts/bootstrap-icons.woff
git_analytics/static/css/fonts/bootstrap-icons.woff2
git_analytics/static/favicon.svg
git_analytics/static/index.html
git_analytics/static/js/bootstrap.bundle.min.js
git_analytics/static/js/chart.umd.min.js
git_analytics/static/js/git-analytics.js
git_analytics/web_app.py
git_analytics-0.1.13.dist-info/LICENSE
git_analytics-0.1.13.dist-info/METADATA
git_analytics-0.1.13.dist-info/WHEEL
git_analytics-0.1.13.dist-info/entry_points.txt
git_analytics-0.1.13.dist-info/RECORD
