Metadata-Version: 2.1
Name: git-analytics
Version: 0.1.13
Summary: Advanced analytics for Git repositories — commits, authors, code churn, lines of code, trends, and visual dashboards.
Home-page: https://git-analytics.com
License: MIT
Keywords: git,git-statistics,git-status,code-metrics,lines-of-code,commit-history,git-analysis,git-metrics,git-commits,repo-stats git-stats,repository-metrics,developer-metrics,git-analytics code-statistics,commit-analysis,git-analyze,git-insights,repo-analysis,git-repo-stats
Author: n0rfas
Author-email: n0rfas@protonmail.com
Requires-Python: >=3.7
Classifier: License :: OSI Approved :: MIT License
Classifier: Programming Language :: Python :: 3
Classifier: Programming Language :: Python :: 3.7
Classifier: Programming Language :: Python :: 3.8
Classifier: Programming Language :: Python :: 3.9
Classifier: Programming Language :: Python :: 3.10
Classifier: Programming Language :: Python :: 3.11
Classifier: Programming Language :: Python :: 3.12
Classifier: Programming Language :: Python :: 3.13
Requires-Dist: GitPython (>=3.1.0,<3.2.0)
Requires-Dist: falcon (>=3.1.0,<3.2.0)
Project-URL: Repository, https://github.com/n0rfas/git-analytics
